{
    "data": "[{\"url\":{},\"meta\":{\"labjs_version\":\"20.1.1\",\"labjs_build\":{\"flavor\":\"production\",\"commit\":\"cd5695f774968f50499757c1423bd95d033ea08e\"},\"location\":\"https://exp01.zih.tu-dresden.de/experiments/raven_task/\",\"userAgent\":\"Mozilla/5.0 (Macintosh; Intel Mac OS X 10_15_7) AppleWebKit/605.1.15 (KHTML, like Gecko) Version/14.1.2 Safari/605.1.15\",\"platform\":\"MacIntel\",\"language\":\"de\",\"locale\":\"de\",\"timeZone\":\"Europe/Berlin\",\"timezoneOffset\":-120,\"screen_width\":1440,\"screen_height\":900,\"scroll_width\":1440,\"scroll_height\":789,\"window_innerWidth\":1440,\"window_innerHeight\":837,\"devicePixelRatio\":1},\"sender\":\"welcome\",\"sender_type\":\"canvas.Screen\",\"sender_id\":\"0\",\"ended_on\":\"timeout\",\"duration\":8010,\"time_run\":2930,\"time_render\":2953,\"time_show\":2968,\"time_end\":10958,\"time_commit\":10959,\"timestamp\":\"2021-08-22T10:08:50.865Z\",\"time_switch\":10978},{\"sender\":\"instructions\",\"sender_type\":\"html.Page\",\"sender_id\":\"1\",\"response\":\"Space\",\"response_action\":\"keypress(Space)\",\"ended_on\":\"response\",\"duration\":5619,\"time_run\":10959,\"time_render\":10958,\"time_show\":10978,\"time_end\":16577,\"time_commit\":16887,\"timestamp\":\"2021-08-22T10:08:56.794Z\",\"time_switch\":17037},{\"sender\":\"example1\",\"sender_type\":\"canvas.Screen\",\"sender_id\":\"2\",\"response\":\"8\",\"response_action\":\"click(0) @8\",\"correctResponse\":\"8\",\"correct\":true,\"ended_on\":\"response\",\"duration\":8682.000000000004,\"time_run\":16888,\"time_render\":16907,\"time_show\":17037,\"time_end\":25589.000000000004,\"time_commit\":25891,\"timestamp\":\"2021-08-22T10:09:05.797Z\",\"time_switch\":25975},{\"sender\":\"example1_feedback\",\"sender_type\":\"canvas.Screen\",\"sender_id\":\"3\",\"response\":\"space\",\"response_action\":\"keypress(Space)\",\"ended_on\":\"response\",\"duration\":751,\"time_run\":25892,\"time_render\":25914,\"time_show\":25975,\"time_end\":26665,\"time_commit\":26968,\"timestamp\":\"2021-08-22T10:09:06.875Z\",\"time_switch\":27100},{\"sender\":\"example2\",\"sender_type\":\"canvas.Screen\",\"sender_id\":\"4\",\"response\":\"4\",\"response_action\":\"click(0) @4\",\"correctResponse\":\"4\",\"correct\":true,\"ended_on\":\"response\",\"duration\":5326.000000000004,\"time_run\":26969,\"time_render\":26984,\"time_show\":27100,\"time_end\":32310.000000000004,\"time_commit\":32613,\"timestamp\":\"2021-08-22T10:09:12.520Z\",\"time_switch\":32693},{\"sender\":\"example2_feedback\",\"sender_type\":\"canvas.Screen\",\"sender_id\":\"5\",\"response\":\"space\",\"response_action\":\"keypress(Space)\",\"ended_on\":\"response\",\"duration\":841,\"time_run\":32615.000000000004,\"time_render\":32632,\"time_show\":32693,\"time_end\":33473,\"time_commit\":33777,\"timestamp\":\"2021-08-22T10:09:13.684Z\",\"time_switch\":33819},{\"sender\":\"get ready\",\"sender_type\":\"canvas.Screen\",\"sender_id\":\"6\",\"response\":\"Space\",\"response_action\":\"keypress(Space)\",\"ended_on\":\"response\",\"duration\":3503,\"time_run\":33777,\"time_render\":33802,\"time_show\":33819,\"time_end\":37305,\"time_commit\":37608.00000000001,\"timestamp\":\"2021-08-22T10:09:17.515Z\",\"time_switch\":37736},{\"sender\":\"test01\",\"sender_type\":\"canvas.Screen\",\"sender_id\":\"7_0\",\"response\":\"8\",\"response_action\":\"click(0) @8\",\"correctResponse\":\"7\",\"correct\":false,\"ended_on\":\"response\",\"duration\":15862,\"time_run\":37608.00000000001,\"time_render\":37629,\"time_show\":37736,\"time_end\":53491,\"time_commit\":53795,\"timestamp\":\"2021-08-22T10:09:33.703Z\",\"time_switch\":53927},{\"sender\":\"test02\",\"sender_type\":\"canvas.Screen\",\"sender_id\":\"7_1\",\"response\":\"4\",\"response_action\":\"click(0) @4\",\"correctResponse\":\"4\",\"correct\":true,\"ended_on\":\"response\",\"duration\":28205,\"time_run\":53796,\"time_render\":53822,\"time_show\":53927,\"time_end\":82027,\"time_commit\":82332.00000000001,\"timestamp\":\"2021-08-22T10:10:02.240Z\",\"time_switch\":82454},{\"sender\":\"test03\",\"sender_type\":\"canvas.Screen\",\"sender_id\":\"7_2\",\"response\":\"6\",\"response_action\":\"click(0) @6\",\"correctResponse\":\"6\",\"correct\":true,\"ended_on\":\"response\",\"duration\":13977,\"time_run\":82332.00000000001,\"time_render\":82348,\"time_show\":82454,\"time_end\":96325,\"time_commit\":96630,\"timestamp\":\"2021-08-22T10:10:16.539Z\",\"time_switch\":96767},{\"sender\":\"test04\",\"sender_type\":\"canvas.Screen\",\"sender_id\":\"7_3\",\"response\":\"2\",\"response_action\":\"click(0) @2\",\"correctResponse\":\"2\",\"correct\":true,\"ended_on\":\"response\",\"duration\":24227,\"time_run\":96630,\"time_render\":96652,\"time_show\":96767,\"time_end\":120879,\"time_commit\":121185,\"timestamp\":\"2021-08-22T10:10:41.095Z\",\"time_switch\":121308},{\"sender\":\"test05\",\"sender_type\":\"canvas.Screen\",\"sender_id\":\"7_4\",\"response\":\"4\",\"response_action\":\"click(0) @4\",\"correctResponse\":\"4\",\"correct\":true,\"ended_on\":\"response\",\"duration\":13009,\"time_run\":121185,\"time_render\":121202,\"time_show\":121308,\"time_end\":134211,\"time_commit\":134518,\"timestamp\":\"2021-08-22T10:10:54.427Z\",\"time_switch\":134644},{\"sender\":\"test06\",\"sender_type\":\"canvas.Screen\",\"sender_id\":\"7_5\",\"response\":\"3\",\"response_action\":\"click(0) @3\",\"correctResponse\":\"7\",\"correct\":false,\"ended_on\":\"response\",\"duration\":23576,\"time_run\":134518,\"time_render\":134538,\"time_show\":134644,\"time_end\":158114,\"time_commit\":158421,\"timestamp\":\"2021-08-22T10:11:18.331Z\",\"time_switch\":158546},{\"sender\":\"test07\",\"sender_type\":\"canvas.Screen\",\"sender_id\":\"7_6\",\"response\":\"4\",\"response_action\":\"click(0) @4\",\"correctResponse\":\"8\",\"correct\":false,\"ended_on\":\"response\",\"duration\":28508,\"time_run\":158421,\"time_render\":158435,\"time_show\":158546,\"time_end\":186943,\"time_commit\":187251,\"timestamp\":\"2021-08-22T10:11:47.163Z\",\"time_switch\":187382},{\"sender\":\"test08\",\"sender_type\":\"canvas.Screen\",\"sender_id\":\"7_7\",\"response\":\"8\",\"response_action\":\"click(0) @8\",\"correctResponse\":\"7\",\"correct\":false,\"ended_on\":\"response\",\"duration\":22399,\"time_run\":187251,\"time_render\":187278,\"time_show\":187382,\"time_end\":209677,\"time_commit\":209985,\"timestamp\":\"2021-08-22T10:12:09.897Z\",\"time_switch\":210112},{\"sender\":\"test09\",\"sender_type\":\"canvas.Screen\",\"sender_id\":\"7_8\",\"response\":\"2\",\"response_action\":\"click(0) @2\",\"correctResponse\":\"5\",\"correct\":false,\"ended_on\":\"response\",\"duration\":12511,\"time_run\":209985,\"time_render\":210006,\"time_show\":210112,\"time_end\":222517,\"time_commit\":222826,\"timestamp\":\"2021-08-22T10:12:22.738Z\",\"time_switch\":222952},{\"sender\":\"test10\",\"sender_type\":\"canvas.Screen\",\"sender_id\":\"7_9\",\"response\":\"1\",\"response_action\":\"click(0) @1\",\"correctResponse\":\"5\",\"correct\":false,\"ended_on\":\"response\",\"duration\":10557,\"time_run\":222826,\"time_render\":222840,\"time_show\":222952,\"time_end\":233397,\"time_commit\":233705,\"timestamp\":\"2021-08-22T10:12:33.618Z\",\"time_switch\":233823},{\"sender\":\"test11\",\"sender_type\":\"canvas.Screen\",\"sender_id\":\"7_10\",\"response\":\"4\",\"response_action\":\"click(0) @4\",\"correctResponse\":\"4\",\"correct\":true,\"ended_on\":\"response\",\"duration\":43438,\"time_run\":233706.00000000003,\"time_render\":233718,\"time_show\":233823,\"time_end\":277156,\"time_commit\":277466,\"timestamp\":\"2021-08-22T10:13:17.381Z\",\"time_switch\":277590},{\"sender\":\"test12\",\"sender_type\":\"canvas.Screen\",\"sender_id\":\"7_11\",\"response\":\"8\",\"response_action\":\"click(0) @8\",\"correctResponse\":\"1\",\"correct\":false,\"ended_on\":\"response\",\"duration\":3866.000000000058,\"time_run\":277467,\"time_render\":277486,\"time_show\":277590,\"time_end\":281352.00000000006,\"time_commit\":281662,\"timestamp\":\"2021-08-22T10:13:21.577Z\",\"time_switch\":281697},{\"sender\":\"tests (15min)\",\"sender_type\":\"flow.Sequence\",\"sender_id\":\"7\",\"ended_on\":\"completion\",\"duration\":243616.00000000006,\"time_run\":37608.00000000001,\"time_render\":37629,\"time_show\":37736,\"time_end\":281352.00000000006,\"time_commit\":281663,\"timestamp\":\"2021-08-22T10:13:21.577Z\",\"time_switch\":281697},{\"sender\":\"good bye\",\"sender_type\":\"canvas.Screen\",\"sender_id\":\"8\",\"ended_on\":\"timeout\",\"duration\":3994,\"time_run\":281663,\"time_render\":281681,\"time_show\":281697,\"time_end\":285674,\"time_commit\":285677,\"timestamp\":\"2021-08-22T10:13:25.591Z\",\"time_switch\":285691},{\"sender\":\"root\",\"sender_type\":\"flow.Sequence\",\"sender_id\":null,\"ended_on\":\"completion\",\"duration\":282706,\"time_run\":2930,\"time_render\":2953,\"time_show\":2968,\"time_end\":285674,\"time_commit\":285677,\"timestamp\":\"2021-08-22T10:13:25.592Z\",\"time_switch\":285691}]",
    "metadata": "{\"slice\":0,\"id\":\"6de825ba-95a1-4d3b-8b28-8a921fe618f8\",\"payload\":\"full\"}",
    "url": "https://exp01.zih.tu-dresden.de/experiments/raven_task/"
}