{
    "data": "[{\"url\":{},\"meta\":{\"labjs_version\":\"20.1.1\",\"labjs_build\":{\"flavor\":\"production\",\"commit\":\"cd5695f774968f50499757c1423bd95d033ea08e\"},\"location\":\"https://exp01.zih.tu-dresden.de/experiments/raven_task/\",\"userAgent\":\"Mozilla/5.0 (Windows NT 10.0; Win64; x64) AppleWebKit/537.36 (KHTML, like Gecko) Chrome/91.0.4472.77 Safari/537.36 Edg/91.0.864.41\",\"platform\":\"Win32\",\"language\":\"de\",\"locale\":\"de\",\"timeZone\":\"Europe/Berlin\",\"timezoneOffset\":-120,\"screen_width\":1536,\"screen_height\":864,\"scroll_width\":1536,\"scroll_height\":706,\"window_innerWidth\":1536,\"window_innerHeight\":754,\"devicePixelRatio\":1.25},\"sender\":\"welcome\",\"sender_type\":\"canvas.Screen\",\"sender_id\":\"0\",\"response\":\"any\",\"response_action\":\"keypress\",\"ended_on\":\"response\",\"duration\":7960.534999999814,\"time_run\":3150.899999999441,\"time_render\":3058.528,\"time_show\":3141.765,\"time_end\":11102.299999999814,\"time_commit\":11107.599999999627,\"timestamp\":\"2021-06-09T09:38:02.920Z\",\"time_switch\":11128.144},{\"sender\":\"instructions\",\"sender_type\":\"html.Page\",\"sender_id\":\"1\",\"response\":\"Space\",\"response_action\":\"keypress(Space)\",\"ended_on\":\"response\",\"duration\":19734.25599999944,\"time_run\":11108.5,\"time_render\":11111.421,\"time_show\":11128.144,\"time_end\":30862.39999999944,\"time_commit\":30873.39999999944,\"timestamp\":\"2021-06-09T09:38:22.686Z\",\"time_switch\":30952.361},{\"sender\":\"example1\",\"sender_type\":\"canvas.Screen\",\"sender_id\":\"2\",\"response\":\"8\",\"response_action\":\"click(0) @8\",\"correctResponse\":\"8\",\"correct\":true,\"ended_on\":\"response\",\"duration\":11316.03899999944,\"time_run\":30873.699999999255,\"time_render\":30869.105,\"time_show\":30952.361,\"time_end\":42268.39999999944,\"time_commit\":42271.299999999814,\"timestamp\":\"2021-06-09T09:38:34.084Z\",\"time_switch\":42356.63},{\"sender\":\"example1_feedback\",\"sender_type\":\"canvas.Screen\",\"sender_id\":\"3\",\"response\":\"space\",\"response_action\":\"keypress(Space)\",\"ended_on\":\"response\",\"duration\":1728.96999999963,\"time_run\":42337.09999999963,\"time_render\":42321.477,\"time_show\":42356.63,\"time_end\":44085.59999999963,\"time_commit\":44087,\"timestamp\":\"2021-06-09T09:38:35.899Z\",\"time_switch\":44090.708},{\"sender\":\"example2\",\"sender_type\":\"canvas.Screen\",\"sender_id\":\"4\",\"response\":\"4\",\"response_action\":\"click(0) @4\",\"correctResponse\":\"4\",\"correct\":true,\"ended_on\":\"response\",\"duration\":3185.591999999815,\"time_run\":44087.199999999255,\"time_render\":44073.3,\"time_show\":44090.708,\"time_end\":47276.299999999814,\"time_commit\":47277.59999999963,\"timestamp\":\"2021-06-09T09:38:39.090Z\",\"time_switch\":47341.967},{\"sender\":\"example2_feedback\",\"sender_type\":\"canvas.Screen\",\"sender_id\":\"5\",\"response\":\"space\",\"response_action\":\"keypress(Space)\",\"ended_on\":\"response\",\"duration\":1239.9329999994443,\"time_run\":47336,\"time_render\":47325.908,\"time_show\":47341.967,\"time_end\":48581.89999999944,\"time_commit\":48583.5,\"timestamp\":\"2021-06-09T09:38:40.396Z\",\"time_switch\":48609.028},{\"sender\":\"get ready\",\"sender_type\":\"canvas.Screen\",\"sender_id\":\"6\",\"response\":\"Space\",\"response_action\":\"keypress(Space)\",\"ended_on\":\"response\",\"duration\":6213.271999999815,\"time_run\":48583.799999999814,\"time_render\":48575.688,\"time_show\":48609.028,\"time_end\":54822.299999999814,\"time_commit\":54824.199999999255,\"timestamp\":\"2021-06-09T09:38:46.637Z\",\"time_switch\":54828.031},{\"sender\":\"test01\",\"sender_type\":\"canvas.Screen\",\"sender_id\":\"7_0\",\"response\":\"7\",\"response_action\":\"click(0) @7\",\"correctResponse\":\"7\",\"correct\":true,\"ended_on\":\"response\",\"duration\":6160.168999999252,\"time_run\":54824.59999999963,\"time_render\":54808.835,\"time_show\":54828.031,\"time_end\":60988.199999999255,\"time_commit\":60989.39999999944,\"timestamp\":\"2021-06-09T09:38:52.802Z\",\"time_switch\":60997.125},{\"sender\":\"test02\",\"sender_type\":\"canvas.Screen\",\"sender_id\":\"7_1\",\"response\":\"3\",\"response_action\":\"click(0) @3\",\"correctResponse\":\"4\",\"correct\":false,\"ended_on\":\"response\",\"duration\":8943.274999999441,\"time_run\":60989.59999999963,\"time_render\":60980.744,\"time_show\":60997.125,\"time_end\":69940.39999999944,\"time_commit\":69941.69999999925,\"timestamp\":\"2021-06-09T09:39:01.754Z\",\"time_switch\":69950.483},{\"sender\":\"test03\",\"sender_type\":\"canvas.Screen\",\"sender_id\":\"7_2\",\"response\":\"2\",\"response_action\":\"click(0) @2\",\"correctResponse\":\"6\",\"correct\":false,\"ended_on\":\"response\",\"duration\":6845.916999999448,\"time_run\":69941.79999999981,\"time_render\":69934.224,\"time_show\":69950.483,\"time_end\":76796.39999999944,\"time_commit\":76797.5,\"timestamp\":\"2021-06-09T09:39:08.610Z\",\"time_switch\":76803.352},{\"sender\":\"test04\",\"sender_type\":\"canvas.Screen\",\"sender_id\":\"7_3\",\"response\":\"2\",\"response_action\":\"click(0) @2\",\"correctResponse\":\"2\",\"correct\":true,\"ended_on\":\"response\",\"duration\":4728.947999999815,\"time_run\":76797.59999999963,\"time_render\":76786.373,\"time_show\":76803.352,\"time_end\":81532.29999999981,\"time_commit\":81533.5,\"timestamp\":\"2021-06-09T09:39:13.346Z\",\"time_switch\":81538.263},{\"sender\":\"test05\",\"sender_type\":\"canvas.Screen\",\"sender_id\":\"7_4\",\"response\":\"3\",\"response_action\":\"click(0) @3\",\"correctResponse\":\"4\",\"correct\":false,\"ended_on\":\"response\",\"duration\":4594.036999999807,\"time_run\":81533.59999999963,\"time_render\":81521.95,\"time_show\":81538.263,\"time_end\":86132.29999999981,\"time_commit\":86133.5,\"timestamp\":\"2021-06-09T09:39:17.946Z\",\"time_switch\":86140.03},{\"sender\":\"test06\",\"sender_type\":\"canvas.Screen\",\"sender_id\":\"7_5\",\"response\":\"7\",\"response_action\":\"click(0) @7\",\"correctResponse\":\"7\",\"correct\":true,\"ended_on\":\"response\",\"duration\":5080.269999999815,\"time_run\":86133.69999999925,\"time_render\":86123.712,\"time_show\":86140.03,\"time_end\":91220.29999999981,\"time_commit\":91221.5,\"timestamp\":\"2021-06-09T09:39:23.034Z\",\"time_switch\":91225.362},{\"sender\":\"test07\",\"sender_type\":\"canvas.Screen\",\"sender_id\":\"7_6\",\"response\":\"4\",\"response_action\":\"click(0) @4\",\"correctResponse\":\"8\",\"correct\":false,\"ended_on\":\"response\",\"duration\":5642.737999999634,\"time_run\":91221.59999999963,\"time_render\":91208.952,\"time_show\":91225.362,\"time_end\":96868.09999999963,\"time_commit\":96869.29999999981,\"timestamp\":\"2021-06-09T09:39:28.682Z\",\"time_switch\":96877.375},{\"sender\":\"test08\",\"sender_type\":\"canvas.Screen\",\"sender_id\":\"7_7\",\"response\":\"1\",\"response_action\":\"click(0) @1\",\"correctResponse\":\"7\",\"correct\":false,\"ended_on\":\"response\",\"duration\":3366.625,\"time_run\":96869.59999999963,\"time_render\":96861.093,\"time_show\":96877.375,\"time_end\":100244,\"time_commit\":100245.09999999963,\"timestamp\":\"2021-06-09T09:39:32.058Z\",\"time_switch\":100262.064},{\"sender\":\"test09\",\"sender_type\":\"canvas.Screen\",\"sender_id\":\"7_8\",\"response\":\"3\",\"response_action\":\"click(0) @3\",\"correctResponse\":\"5\",\"correct\":false,\"ended_on\":\"response\",\"duration\":3782.3359999994427,\"time_run\":100245.29999999981,\"time_render\":100229.081,\"time_show\":100262.064,\"time_end\":104044.39999999944,\"time_commit\":104045.5,\"timestamp\":\"2021-06-09T09:39:35.858Z\",\"time_switch\":104063.576},{\"sender\":\"test10\",\"sender_type\":\"canvas.Screen\",\"sender_id\":\"7_9\",\"response\":\"8\",\"response_action\":\"click(0) @8\",\"correctResponse\":\"5\",\"correct\":false,\"ended_on\":\"response\",\"duration\":2876.3239999994403,\"time_run\":104045.59999999963,\"time_render\":104046.836,\"time_show\":104063.576,\"time_end\":106939.89999999944,\"time_commit\":106940.89999999944,\"timestamp\":\"2021-06-09T09:39:38.753Z\",\"time_switch\":106947.988},{\"sender\":\"test11\",\"sender_type\":\"canvas.Screen\",\"sender_id\":\"7_10\",\"response\":\"4\",\"response_action\":\"click(0) @4\",\"correctResponse\":\"4\",\"correct\":true,\"ended_on\":\"response\",\"duration\":4360.411999999444,\"time_run\":106941.09999999963,\"time_render\":106931.63,\"time_show\":106947.988,\"time_end\":111308.39999999944,\"time_commit\":111309.59999999963,\"timestamp\":\"2021-06-09T09:39:43.122Z\",\"time_switch\":111316.562},{\"sender\":\"test12\",\"sender_type\":\"canvas.Screen\",\"sender_id\":\"7_11\",\"response\":\"2\",\"response_action\":\"click(0) @2\",\"correctResponse\":\"1\",\"correct\":false,\"ended_on\":\"response\",\"duration\":4967.437999999995,\"time_run\":111309.69999999925,\"time_render\":111299.549,\"time_show\":111316.562,\"time_end\":116284,\"time_commit\":116285.09999999963,\"timestamp\":\"2021-06-09T09:39:48.098Z\",\"time_switch\":116301.526},{\"sender\":\"tests (15min)\",\"sender_type\":\"flow.Sequence\",\"sender_id\":\"7\",\"ended_on\":\"completion\",\"duration\":61455.969,\"time_run\":54824.5,\"time_render\":54808.835,\"time_show\":54828.031,\"time_end\":116284,\"time_commit\":116286.89999999944,\"timestamp\":\"2021-06-09T09:39:48.099Z\",\"time_switch\":116301.526},{\"sender\":\"good bye\",\"sender_type\":\"canvas.Screen\",\"sender_id\":\"8\",\"ended_on\":\"timeout\",\"duration\":4001.8899999999994,\"time_run\":116287,\"time_render\":116284.851,\"time_show\":116301.526,\"time_end\":120286.743,\"time_commit\":120288,\"timestamp\":\"2021-06-09T09:39:52.100Z\",\"time_switch\":120303.416},{\"sender\":\"root\",\"sender_type\":\"flow.Sequence\",\"sender_id\":null,\"ended_on\":\"completion\",\"duration\":117144.978,\"time_run\":3150.699999999255,\"time_render\":3058.528,\"time_show\":3141.765,\"time_end\":120286.743,\"time_commit\":120288.59999999963,\"timestamp\":\"2021-06-09T09:39:52.101Z\",\"time_switch\":120303.416}]",
    "metadata": "{\"slice\":0,\"id\":\"10f441f9-7d13-4833-926c-a5ea2e56d4a3\",\"payload\":\"full\"}",
    "url": "https://exp01.zih.tu-dresden.de/experiments/raven_task/"
}