{
    "data": "[{\"url\":{},\"meta\":{\"labjs_version\":\"20.1.1\",\"labjs_build\":{\"flavor\":\"production\",\"commit\":\"cd5695f774968f50499757c1423bd95d033ea08e\"},\"location\":\"https://exp02.zih.tu-dresden.de/experiments/spot_a_word_task/\",\"userAgent\":\"Mozilla/5.0 (Windows NT 6.3; Win64; x64; rv:89.0) Gecko/20100101 Firefox/89.0\",\"platform\":\"Win32\",\"language\":\"de\",\"locale\":\"de\",\"timeZone\":\"Europe/Berlin\",\"timezoneOffset\":-120,\"screen_width\":1280,\"screen_height\":720,\"scroll_width\":1280,\"scroll_height\":598,\"window_innerWidth\":1280,\"window_innerHeight\":598,\"devicePixelRatio\":1.5},\"sender\":\"start_html\",\"sender_type\":\"html.Screen\",\"sender_id\":\"0\",\"ended_on\":\"timeout\",\"duration\":6017.08,\"time_run\":459,\"time_render\":569.92,\"time_show\":586.6,\"time_end\":6570.34,\"time_commit\":6573,\"timestamp\":\"2021-08-08T15:07:34.970Z\",\"time_switch\":6603.68},{\"sender\":\"manual_html\",\"sender_type\":\"html.Screen\",\"sender_id\":\"1\",\"response\":\"space\",\"response_action\":\"keypress(Space)\",\"ended_on\":\"response\",\"duration\":23223.32,\"time_run\":6573,\"time_render\":6570.34,\"time_show\":6603.68,\"time_end\":29827,\"time_commit\":29841,\"timestamp\":\"2021-08-08T15:07:58.239Z\",\"time_switch\":29888.22},{\"sender\":\"example1_screen\",\"sender_type\":\"canvas.Screen\",\"sender_id\":\"2\",\"response\":\"4\",\"response_action\":\"keypress(4)\",\"correctResponse\":\"4\",\"correct\":true,\"ended_on\":\"response\",\"duration\":2329.779999999999,\"time_run\":29872,\"time_render\":29872.28,\"time_show\":29888.22,\"time_end\":32218,\"time_commit\":32231,\"timestamp\":\"2021-08-08T15:08:00.628Z\",\"time_switch\":32271.68},{\"sender\":\"example1_feedback\",\"sender_type\":\"canvas.Screen\",\"sender_id\":\"3\",\"response\":\"Space\",\"response_action\":\"keypress(Space)\",\"ended_on\":\"response\",\"duration\":4649.32,\"time_run\":32240,\"time_render\":32240,\"time_show\":32271.68,\"time_end\":36921,\"time_commit\":36938,\"timestamp\":\"2021-08-08T15:08:05.336Z\",\"time_switch\":36988.6},{\"sender\":\"example2_screen\",\"sender_type\":\"canvas.Screen\",\"sender_id\":\"4\",\"response\":\"5\",\"response_action\":\"keypress(5)\",\"correctResponse\":\"5\",\"correct\":true,\"ended_on\":\"response\",\"duration\":2401.4000000000015,\"time_run\":36955,\"time_render\":36954.96,\"time_show\":36988.6,\"time_end\":39390,\"time_commit\":39402,\"timestamp\":\"2021-08-08T15:08:07.800Z\",\"time_switch\":39438.74},{\"sender\":\"example2_feedback\",\"sender_type\":\"canvas.Screen\",\"sender_id\":\"5\",\"response\":\"Space\",\"response_action\":\"keypress(Space)\",\"ended_on\":\"response\",\"duration\":1373.260000000002,\"time_run\":39417,\"time_render\":39416.82,\"time_show\":39438.74,\"time_end\":40812,\"time_commit\":40815,\"timestamp\":\"2021-08-08T15:08:09.212Z\",\"time_switch\":40838.76},{\"sender\":\"example3_screen\",\"sender_type\":\"canvas.Screen\",\"sender_id\":\"6\",\"response\":\"1\",\"response_action\":\"keypress(1)\",\"correctResponse\":\"1\",\"correct\":true,\"ended_on\":\"response\",\"duration\":1301.239999999998,\"time_run\":40824,\"time_render\":40824.52,\"time_show\":40838.76,\"time_end\":42140,\"time_commit\":42152,\"timestamp\":\"2021-08-08T15:08:10.550Z\",\"time_switch\":42188.74},{\"sender\":\"example3_feedback\",\"sender_type\":\"canvas.Screen\",\"sender_id\":\"7\",\"response\":\"Space\",\"response_action\":\"keypress(Space)\",\"ended_on\":\"response\",\"duration\":2591.260000000002,\"time_run\":42160,\"time_render\":42160.54,\"time_show\":42188.74,\"time_end\":44780,\"time_commit\":44787,\"timestamp\":\"2021-08-08T15:08:13.184Z\",\"time_switch\":44805.48},{\"sender\":\"get_ready_html\",\"sender_type\":\"html.Screen\",\"sender_id\":\"8\",\"response\":\"space\",\"response_action\":\"keypress(Space)\",\"ended_on\":\"response\",\"duration\":5896.519999999997,\"time_run\":44787,\"time_render\":44787.94,\"time_show\":44805.48,\"time_end\":50702,\"time_commit\":50717,\"timestamp\":\"2021-08-08T15:08:19.114Z\",\"time_switch\":50805.94},{\"sender\":\"trial_screen\",\"sender_type\":\"canvas.Screen\",\"sender_id\":\"9_0\",\"correct\":true,\"trial_ID\":1,\"word1\":\"siziol\",\"word2\":\"salzahl\",\"word3\":\"sozihl\",\"word4\":\"sziam\",\"word5\":\"sozial\",\"response\":\"5\",\"response_action\":\"keypress(5)\",\"correctResponse\":\"5\",\"ended_on\":\"response\",\"duration\":1647.0599999999977,\"time_run\":50785,\"time_render\":50785.28,\"time_show\":50805.94,\"time_end\":52453,\"time_commit\":52465,\"timestamp\":\"2021-08-08T15:08:20.863Z\",\"time_switch\":52522.7},{\"sender\":\"trial_screen\",\"sender_type\":\"canvas.Screen\",\"sender_id\":\"9_1\",\"correct\":true,\"trial_ID\":2,\"word1\":\"Lamone\",\"word2\":\"Talane\",\"word3\":\"Matrone\",\"word4\":\"Tarone\",\"word5\":\"Malonte\",\"response\":\"3\",\"response_action\":\"keypress(3)\",\"correctResponse\":\"3\",\"ended_on\":\"response\",\"duration\":4101.300000000003,\"time_run\":52483,\"time_render\":52482.66,\"time_show\":52522.7,\"time_end\":56624,\"time_commit\":56631,\"timestamp\":\"2021-08-08T15:08:25.028Z\",\"time_switch\":56689.56},{\"sender\":\"trial_screen\",\"sender_type\":\"canvas.Screen\",\"sender_id\":\"9_2\",\"correct\":true,\"trial_ID\":3,\"word1\":\"kurinesisch\",\"word2\":\"kulinarisch\",\"word3\":\"kumenisch\",\"word4\":\"kulissarisch\",\"word5\":\"kannastrisch\",\"response\":\"2\",\"response_action\":\"keypress(2)\",\"correctResponse\":\"2\",\"ended_on\":\"response\",\"duration\":3231.4400000000023,\"time_run\":56649,\"time_render\":56649.14,\"time_show\":56689.56,\"time_end\":59921,\"time_commit\":59934,\"timestamp\":\"2021-08-08T15:08:28.333Z\",\"time_switch\":59973.08},{\"sender\":\"trial_screen\",\"sender_type\":\"canvas.Screen\",\"sender_id\":\"9_3\",\"correct\":true,\"trial_ID\":4,\"word1\":\"Tinxur\",\"word2\":\"Kukutur\",\"word3\":\"Fraktan\",\"word4\":\"Tinktur\",\"word5\":\"Rimsuhr\",\"response\":\"4\",\"response_action\":\"keypress(4)\",\"correctResponse\":\"4\",\"ended_on\":\"response\",\"duration\":2556.9199999999983,\"time_run\":59948,\"time_render\":59948.28,\"time_show\":59973.08,\"time_end\":62530,\"time_commit\":62543,\"timestamp\":\"2021-08-08T15:08:30.940Z\",\"time_switch\":62606.56},{\"sender\":\"trial_screen\",\"sender_type\":\"canvas.Screen\",\"sender_id\":\"9_4\",\"correct\":false,\"trial_ID\":5,\"word1\":\"beralen\",\"word2\":\"ger\u00e4ltet\",\"word3\":\"an\u00e4lteren\",\"word4\":\"unt\u00e4ren\",\"word5\":\"verbr\u00e4men\",\"response\":\"4\",\"response_action\":\"keypress(4)\",\"correctResponse\":\"5\",\"ended_on\":\"response\",\"duration\":9611.440000000002,\"time_run\":62558,\"time_render\":62557.5,\"time_show\":62606.56,\"time_end\":72218,\"time_commit\":72229,\"timestamp\":\"2021-08-08T15:08:40.626Z\",\"time_switch\":72273.7},{\"sender\":\"trial_screen\",\"sender_type\":\"canvas.Screen\",\"sender_id\":\"9_5\",\"correct\":true,\"trial_ID\":6,\"word1\":\"Rosto\",\"word2\":\"Torso\",\"word3\":\"Soro\",\"word4\":\"Torgos\",\"word5\":\"Tosor\",\"response\":\"2\",\"response_action\":\"keypress(2)\",\"correctResponse\":\"2\",\"ended_on\":\"response\",\"duration\":3944.300000000003,\"time_run\":72241,\"time_render\":72240.52,\"time_show\":72273.7,\"time_end\":76218,\"time_commit\":76223,\"timestamp\":\"2021-08-08T15:08:44.620Z\",\"time_switch\":76257.22},{\"sender\":\"trial_screen\",\"sender_type\":\"canvas.Screen\",\"sender_id\":\"9_6\",\"correct\":true,\"trial_ID\":7,\"word1\":\"Redor\",\"word2\":\"Radium\",\"word3\":\"Terion\",\"word4\":\"Dramin\",\"word5\":\"Orakium\",\"response\":\"2\",\"response_action\":\"keypress(2)\",\"correctResponse\":\"2\",\"ended_on\":\"response\",\"duration\":1460.7799999999988,\"time_run\":76235,\"time_render\":76235.14,\"time_show\":76257.22,\"time_end\":77718,\"time_commit\":77727,\"timestamp\":\"2021-08-08T15:08:46.125Z\",\"time_switch\":77774},{\"sender\":\"trial_screen\",\"sender_type\":\"canvas.Screen\",\"sender_id\":\"9_7\",\"correct\":true,\"trial_ID\":8,\"word1\":\"Nale\",\"word2\":\"Sahe\",\"word3\":\"Nase\",\"word4\":\"Nesa\",\"word5\":\"Sehna\",\"response\":\"3\",\"response_action\":\"keypress(3)\",\"correctResponse\":\"3\",\"ended_on\":\"response\",\"duration\":3741,\"time_run\":77739,\"time_render\":77738.66,\"time_show\":77774,\"time_end\":81515,\"time_commit\":81527,\"timestamp\":\"2021-08-08T15:08:49.924Z\",\"time_switch\":81557.52},{\"sender\":\"trial_screen\",\"sender_type\":\"canvas.Screen\",\"sender_id\":\"9_8\",\"correct\":false,\"trial_ID\":9,\"word1\":\"Rilkiase\",\"word2\":\"Kilister\",\"word3\":\"Riliker\",\"word4\":\"Klistier\",\"word5\":\"Linkure\",\"response\":\"2\",\"response_action\":\"keypress(2)\",\"correctResponse\":\"4\",\"ended_on\":\"response\",\"duration\":5613.479999999996,\"time_run\":81535,\"time_render\":81535.24,\"time_show\":81557.52,\"time_end\":87171,\"time_commit\":87185,\"timestamp\":\"2021-08-08T15:08:55.583Z\",\"time_switch\":87224.46},{\"sender\":\"trial_screen\",\"sender_type\":\"canvas.Screen\",\"sender_id\":\"9_9\",\"correct\":true,\"trial_ID\":10,\"word1\":\"kentern\",\"word2\":\"knerte\",\"word3\":\"kanzen\",\"word4\":\"kretern\",\"word5\":\"trekern\",\"response\":\"1\",\"response_action\":\"keypress(1)\",\"correctResponse\":\"1\",\"ended_on\":\"response\",\"duration\":6008.539999999994,\"time_run\":87199,\"time_render\":87199,\"time_show\":87224.46,\"time_end\":93233,\"time_commit\":93255,\"timestamp\":\"2021-08-08T15:09:01.652Z\",\"time_switch\":93308.08},{\"sender\":\"trial_screen\",\"sender_type\":\"canvas.Screen\",\"sender_id\":\"9_10\",\"correct\":true,\"trial_ID\":11,\"word1\":\"Sorekin\",\"word2\":\"Sarowin\",\"word3\":\"Rosakin\",\"word4\":\"Narosin\",\"word5\":\"Kerosin\",\"response\":\"5\",\"response_action\":\"keypress(5)\",\"correctResponse\":\"5\",\"ended_on\":\"response\",\"duration\":2534.9199999999983,\"time_run\":93285,\"time_render\":93285.86,\"time_show\":93308.08,\"time_end\":95843,\"time_commit\":95847,\"timestamp\":\"2021-08-08T15:09:04.245Z\",\"time_switch\":95891.58},{\"sender\":\"trial_screen\",\"sender_type\":\"canvas.Screen\",\"sender_id\":\"9_11\",\"correct\":true,\"trial_ID\":12,\"word1\":\"Ralke\",\"word2\":\"Korre\",\"word3\":\"Ruckse\",\"word4\":\"Recke\",\"word5\":\"Ulte\",\"response\":\"4\",\"response_action\":\"keypress(4)\",\"correctResponse\":\"4\",\"ended_on\":\"response\",\"duration\":2404.4199999999983,\"time_run\":95867,\"time_render\":95867.2,\"time_show\":95891.58,\"time_end\":98296,\"time_commit\":98311,\"timestamp\":\"2021-08-08T15:09:06.708Z\",\"time_switch\":98358.38},{\"sender\":\"trial_screen\",\"sender_type\":\"canvas.Screen\",\"sender_id\":\"9_12\",\"correct\":true,\"trial_ID\":13,\"word1\":\"Kapaun\",\"word2\":\"Paukan\",\"word3\":\"Naupack\",\"word4\":\"Aupeck\",\"word5\":\"Ankepran\",\"response\":\"1\",\"response_action\":\"keypress(1)\",\"correctResponse\":\"1\",\"ended_on\":\"response\",\"duration\":3296.6199999999953,\"time_run\":98332,\"time_render\":98332.34,\"time_show\":98358.38,\"time_end\":101655,\"time_commit\":101666,\"timestamp\":\"2021-08-08T15:09:10.064Z\",\"time_switch\":101708.42},{\"sender\":\"trial_screen\",\"sender_type\":\"canvas.Screen\",\"sender_id\":\"9_13\",\"correct\":false,\"trial_ID\":14,\"word1\":\"Dissonanz\",\"word2\":\"Diskrisanz\",\"word3\":\"Distranz\",\"word4\":\"Dinotanz\",\"word5\":\"Sidonenz\",\"response\":\"4\",\"response_action\":\"keypress(4)\",\"correctResponse\":\"1\",\"ended_on\":\"response\",\"duration\":3978.5800000000017,\"time_run\":101683,\"time_render\":101682.62,\"time_show\":101708.42,\"time_end\":105687,\"time_commit\":105693,\"timestamp\":\"2021-08-08T15:09:14.091Z\",\"time_switch\":105725.38},{\"sender\":\"trial_screen\",\"sender_type\":\"canvas.Screen\",\"sender_id\":\"9_14\",\"correct\":true,\"trial_ID\":15,\"word1\":\"Kirse\",\"word2\":\"Sirke\",\"word3\":\"Krise\",\"word4\":\"Krospe\",\"word5\":\"Seris\",\"response\":\"3\",\"response_action\":\"keypress(3)\",\"correctResponse\":\"3\",\"ended_on\":\"response\",\"duration\":2305.6199999999953,\"time_run\":105711,\"time_render\":105710.16,\"time_show\":105725.38,\"time_end\":108031,\"time_commit\":108035,\"timestamp\":\"2021-08-08T15:09:16.432Z\",\"time_switch\":108092.06},{\"sender\":\"trial_screen\",\"sender_type\":\"canvas.Screen\",\"sender_id\":\"9_15\",\"correct\":true,\"trial_ID\":16,\"word1\":\"Tume\",\"word2\":\"Umat\",\"word3\":\"Maut\",\"word4\":\"Taum\",\"word5\":\"Muta\",\"response\":\"3\",\"response_action\":\"keypress(3)\",\"correctResponse\":\"3\",\"ended_on\":\"response\",\"duration\":1672.9400000000023,\"time_run\":108050,\"time_render\":108049.88,\"time_show\":108092.06,\"time_end\":109765,\"time_commit\":109780,\"timestamp\":\"2021-08-08T15:09:18.177Z\",\"time_switch\":109842.3},{\"sender\":\"trial_screen\",\"sender_type\":\"canvas.Screen\",\"sender_id\":\"9_16\",\"correct\":true,\"trial_ID\":17,\"word1\":\"Tuhl\",\"word2\":\"Lar\",\"word3\":\"Lest\",\"word4\":\"Dall\",\"word5\":\"Lid\",\"response\":\"5\",\"response_action\":\"keypress(5)\",\"correctResponse\":\"5\",\"ended_on\":\"response\",\"duration\":3172.699999999997,\"time_run\":109798,\"time_render\":109798.02,\"time_show\":109842.3,\"time_end\":113015,\"time_commit\":113025,\"timestamp\":\"2021-08-08T15:09:21.422Z\",\"time_switch\":113059.08},{\"sender\":\"trial_screen\",\"sender_type\":\"canvas.Screen\",\"sender_id\":\"9_17\",\"correct\":false,\"trial_ID\":18,\"word1\":\"Adept\",\"word2\":\"Padet\",\"word3\":\"Edapt\",\"word4\":\"Epatt\",\"word5\":\"Taped\",\"response\":\"5\",\"response_action\":\"keypress(5)\",\"correctResponse\":\"1\",\"ended_on\":\"response\",\"duration\":8861.919999999998,\"time_run\":113038,\"time_render\":113037.6,\"time_show\":113059.08,\"time_end\":121921,\"time_commit\":121935,\"timestamp\":\"2021-08-08T15:09:30.333Z\",\"time_switch\":121976.22},{\"sender\":\"trial_screen\",\"sender_type\":\"canvas.Screen\",\"sender_id\":\"9_18\",\"correct\":true,\"trial_ID\":19,\"word1\":\"Spirine\",\"word2\":\"Saprin\",\"word3\":\"Parsin\",\"word4\":\"Purin\",\"word5\":\"Asprint\",\"response\":\"4\",\"response_action\":\"keypress(4)\",\"correctResponse\":\"4\",\"ended_on\":\"response\",\"duration\":4835.779999999999,\"time_run\":121954,\"time_render\":121953.72,\"time_show\":121976.22,\"time_end\":126812,\"time_commit\":126823,\"timestamp\":\"2021-08-08T15:09:35.220Z\",\"time_switch\":126859.78},{\"sender\":\"trial_screen\",\"sender_type\":\"canvas.Screen\",\"sender_id\":\"9_19\",\"correct\":true,\"trial_ID\":20,\"word1\":\"Kulon\",\"word2\":\"Solgun\",\"word3\":\"Koskan\",\"word4\":\"Soran\",\"word5\":\"Klonus\",\"response\":\"5\",\"response_action\":\"keypress(5)\",\"correctResponse\":\"5\",\"ended_on\":\"response\",\"duration\":6264.220000000001,\"time_run\":126840,\"time_render\":126840.18,\"time_show\":126859.78,\"time_end\":133124,\"time_commit\":133135,\"timestamp\":\"2021-08-08T15:09:41.532Z\",\"time_switch\":133160.1},{\"sender\":\"trial_screen\",\"sender_type\":\"canvas.Screen\",\"sender_id\":\"9_20\",\"correct\":false,\"trial_ID\":21,\"word1\":\"Tronke\",\"word2\":\"Nocktherm\",\"word3\":\"Teronk\",\"word4\":\"Komtur\",\"word5\":\"Rocktur\",\"response\":\"5\",\"response_action\":\"keypress(5)\",\"correctResponse\":\"4\",\"ended_on\":\"response\",\"duration\":4822.899999999994,\"time_run\":133144,\"time_render\":133144.18,\"time_show\":133160.1,\"time_end\":137983,\"time_commit\":138001,\"timestamp\":\"2021-08-08T15:09:46.397Z\",\"time_switch\":138043.68},{\"sender\":\"trial_screen\",\"sender_type\":\"canvas.Screen\",\"sender_id\":\"9_21\",\"correct\":true,\"trial_ID\":22,\"word1\":\"Ripat\",\"word2\":\"Patinatte\",\"word3\":\"Tapir\",\"word4\":\"Apitt\",\"word5\":\"Padir\",\"response\":\"3\",\"response_action\":\"keypress(3)\",\"correctResponse\":\"3\",\"ended_on\":\"response\",\"duration\":2268.320000000007,\"time_run\":138014,\"time_render\":138014.32,\"time_show\":138043.68,\"time_end\":140312,\"time_commit\":140322,\"timestamp\":\"2021-08-08T15:09:48.720Z\",\"time_switch\":140360.46},{\"sender\":\"trial_screen\",\"sender_type\":\"canvas.Screen\",\"sender_id\":\"9_22\",\"correct\":true,\"trial_ID\":23,\"word1\":\"Akifer\",\"word2\":\"Fiaker\",\"word3\":\"Kiaffa\",\"word4\":\"Sariffer\",\"word5\":\"Refisker\",\"response\":\"2\",\"response_action\":\"keypress(2)\",\"correctResponse\":\"2\",\"ended_on\":\"response\",\"duration\":3669.540000000008,\"time_run\":140337,\"time_render\":140337.58,\"time_show\":140360.46,\"time_end\":144030,\"time_commit\":144048,\"timestamp\":\"2021-08-08T15:09:52.446Z\",\"time_switch\":144077.34},{\"sender\":\"trial_screen\",\"sender_type\":\"canvas.Screen\",\"sender_id\":\"9_23\",\"correct\":true,\"trial_ID\":24,\"word1\":\"Kleiber\",\"word2\":\"Beikel\",\"word3\":\"Keibel\",\"word4\":\"Reikler\",\"word5\":\"Biekerl\",\"response\":\"1\",\"response_action\":\"keypress(1)\",\"correctResponse\":\"1\",\"ended_on\":\"response\",\"duration\":3312.6600000000035,\"time_run\":144057,\"time_render\":144057,\"time_show\":144077.34,\"time_end\":147390,\"time_commit\":147396,\"timestamp\":\"2021-08-08T15:09:55.793Z\",\"time_switch\":147444.18},{\"sender\":\"trial_screen\",\"sender_type\":\"canvas.Screen\",\"sender_id\":\"9_24\",\"correct\":true,\"trial_ID\":25,\"word1\":\"Ig\u00e4de\",\"word2\":\"D\u00e4gie\",\"word3\":\"\u00c4gide\",\"word4\":\"Dig\u00e4de\",\"word5\":\"Giad\",\"response\":\"3\",\"response_action\":\"keypress(3)\",\"correctResponse\":\"3\",\"ended_on\":\"response\",\"duration\":5664.820000000007,\"time_run\":147407,\"time_render\":147407.08,\"time_show\":147444.18,\"time_end\":153109,\"time_commit\":153125,\"timestamp\":\"2021-08-08T15:10:01.522Z\",\"time_switch\":153177.8},{\"sender\":\"trial_screen\",\"sender_type\":\"canvas.Screen\",\"sender_id\":\"9_25\",\"correct\":true,\"trial_ID\":26,\"word1\":\"Rixal\",\"word2\":\"Irtax\",\"word3\":\"Rackizie\",\"word4\":\"Matrix\",\"word5\":\"Atrige\",\"response\":\"4\",\"response_action\":\"keypress(4)\",\"correctResponse\":\"4\",\"ended_on\":\"response\",\"duration\":3071.2000000000116,\"time_run\":153138,\"time_render\":153138.72,\"time_show\":153177.8,\"time_end\":156249,\"time_commit\":156264,\"timestamp\":\"2021-08-08T15:10:04.661Z\",\"time_switch\":156294.6},{\"sender\":\"trial_screen\",\"sender_type\":\"canvas.Screen\",\"sender_id\":\"9_26\",\"correct\":false,\"trial_ID\":27,\"word1\":\"Haskisch\",\"word2\":\"Asmisch\",\"word3\":\"Schisma\",\"word4\":\"Rasthmie\",\"word5\":\"Ilschah\",\"response\":\"2\",\"response_action\":\"keypress(2)\",\"correctResponse\":\"3\",\"ended_on\":\"response\",\"duration\":6313.399999999994,\"time_run\":156275,\"time_render\":156275.4,\"time_show\":156294.6,\"time_end\":162608,\"time_commit\":162615,\"timestamp\":\"2021-08-08T15:10:11.012Z\",\"time_switch\":162661.6},{\"sender\":\"trial_screen\",\"sender_type\":\"canvas.Screen\",\"sender_id\":\"9_27\",\"correct\":false,\"trial_ID\":28,\"word1\":\"Sallose\",\"word2\":\"Lordose\",\"word3\":\"Dormase\",\"word4\":\"Rollase\",\"word5\":\"Ardierole\",\"response\":\"5\",\"response_action\":\"keypress(5)\",\"correctResponse\":\"2\",\"ended_on\":\"response\",\"duration\":7385.399999999994,\"time_run\":162626,\"time_render\":162626.16,\"time_show\":162661.6,\"time_end\":170047,\"time_commit\":170052,\"timestamp\":\"2021-08-08T15:10:18.449Z\",\"time_switch\":170112},{\"sender\":\"trial_screen\",\"sender_type\":\"canvas.Screen\",\"sender_id\":\"9_28\",\"correct\":false,\"trial_ID\":29,\"word1\":\"Intranotion\",\"word2\":\"Infranatura\",\"word3\":\"Internodium\",\"word4\":\"Indotalie\",\"word5\":\"Indosta\",\"response\":\"2\",\"response_action\":\"keypress(2)\",\"correctResponse\":\"3\",\"ended_on\":\"response\",\"duration\":3966,\"time_run\":170065,\"time_render\":170064.3,\"time_show\":170112,\"time_end\":174078,\"time_commit\":174084,\"timestamp\":\"2021-08-08T15:10:22.481Z\",\"time_switch\":174128.78},{\"sender\":\"trial_screen\",\"sender_type\":\"canvas.Screen\",\"sender_id\":\"9_29\",\"correct\":true,\"trial_ID\":30,\"word1\":\"Idaste\",\"word2\":\"Dastrix\",\"word3\":\"Astike\",\"word4\":\"Sadile\",\"word5\":\"Kasside\",\"response\":\"5\",\"response_action\":\"keypress(5)\",\"correctResponse\":\"5\",\"ended_on\":\"response\",\"duration\":4933.220000000001,\"time_run\":174112,\"time_render\":174111.8,\"time_show\":174128.78,\"time_end\":179062,\"time_commit\":179066,\"timestamp\":\"2021-08-08T15:10:27.463Z\",\"time_switch\":179095.78},{\"sender\":\"trial_screen\",\"sender_type\":\"canvas.Screen\",\"sender_id\":\"9_30\",\"correct\":true,\"trial_ID\":31,\"word1\":\"Libration\",\"word2\":\"Bilation\",\"word3\":\"Arlation\",\"word4\":\"Iberation\",\"word5\":\"Tiradon\",\"response\":\"1\",\"response_action\":\"keypress(1)\",\"correctResponse\":\"1\",\"ended_on\":\"response\",\"duration\":6559.220000000001,\"time_run\":179085,\"time_render\":179084.58,\"time_show\":179095.78,\"time_end\":185655,\"time_commit\":185664,\"timestamp\":\"2021-08-08T15:10:34.062Z\",\"time_switch\":185712.78},{\"sender\":\"trial_screen\",\"sender_type\":\"canvas.Screen\",\"sender_id\":\"9_31\",\"correct\":false,\"trial_ID\":32,\"word1\":\"Pucker\",\"word2\":\"Keuper\",\"word3\":\"Eucker\",\"word4\":\"Reuspeck\",\"word5\":\"Urkane\",\"response\":\"1\",\"response_action\":\"keypress(1)\",\"correctResponse\":\"2\",\"ended_on\":\"response\",\"duration\":4677.220000000001,\"time_run\":185685,\"time_render\":185685.44,\"time_show\":185712.78,\"time_end\":190390,\"time_commit\":190401,\"timestamp\":\"2021-08-08T15:10:38.798Z\",\"time_switch\":190429.66},{\"sender\":\"trial_screen\",\"sender_type\":\"canvas.Screen\",\"sender_id\":\"9_32\",\"correct\":true,\"trial_ID\":33,\"word1\":\"Sickaber\",\"word2\":\"Bassiker\",\"word3\":\"Kassiber\",\"word4\":\"Sassiker\",\"word5\":\"Askiber\",\"response\":\"3\",\"response_action\":\"keypress(3)\",\"correctResponse\":\"3\",\"ended_on\":\"response\",\"duration\":6225.3399999999965,\"time_run\":190410,\"time_render\":190410.42,\"time_show\":190429.66,\"time_end\":196655,\"time_commit\":196674,\"timestamp\":\"2021-08-08T15:10:45.071Z\",\"time_switch\":196713.36},{\"sender\":\"trial_screen\",\"sender_type\":\"canvas.Screen\",\"sender_id\":\"9_33\",\"correct\":false,\"trial_ID\":34,\"word1\":\"Alquallon\",\"word2\":\"Lisqualien\",\"word3\":\"Talquallen\",\"word4\":\"Quisquilien\",\"word5\":\"Rielquellen\",\"response\":\"3\",\"response_action\":\"keypress(3)\",\"correctResponse\":\"4\",\"ended_on\":\"response\",\"duration\":3285.640000000014,\"time_run\":196689,\"time_render\":196689.2,\"time_show\":196713.36,\"time_end\":199999,\"time_commit\":200011,\"timestamp\":\"2021-08-08T15:10:48.408Z\",\"time_switch\":200046.86},{\"sender\":\"trial_screen\",\"sender_type\":\"canvas.Screen\",\"sender_id\":\"9_34\",\"correct\":false,\"trial_ID\":35,\"word1\":\"Berkiza\",\"word2\":\"Brekzie\",\"word3\":\"Birakzie\",\"word4\":\"Brikazie\",\"word5\":\"Bakiria\",\"response\":\"4\",\"response_action\":\"keypress(4)\",\"correctResponse\":\"2\",\"ended_on\":\"response\",\"duration\":6625.140000000014,\"time_run\":200026,\"time_render\":200026.64,\"time_show\":200046.86,\"time_end\":206672,\"time_commit\":206688,\"timestamp\":\"2021-08-08T15:10:55.086Z\",\"time_switch\":206697.22},{\"sender\":\"loop_trial\",\"sender_type\":\"flow.Loop\",\"sender_id\":\"9\",\"ended_on\":\"completion\",\"duration\":155866.06,\"time_run\":50779,\"time_render\":50785.28,\"time_show\":50805.94,\"time_end\":206672,\"time_commit\":206690,\"timestamp\":\"2021-08-08T15:10:55.087Z\",\"time_switch\":206697.22},{\"sender\":\"end_html\",\"sender_type\":\"html.Screen\",\"sender_id\":\"10\",\"ended_on\":\"timeout\",\"duration\":6000.239999999991,\"time_run\":206691,\"time_render\":206690.9,\"time_show\":206697.22,\"time_end\":212680.8,\"time_commit\":212681,\"timestamp\":\"2021-08-08T15:11:01.079Z\",\"time_switch\":212697.46},{\"sender\":\"root\",\"sender_type\":\"flow.Sequence\",\"sender_id\":null,\"ended_on\":\"completion\",\"duration\":212094.19999999998,\"time_run\":458,\"time_render\":569.92,\"time_show\":586.6,\"time_end\":212680.8,\"time_commit\":212682,\"timestamp\":\"2021-08-08T15:11:01.080Z\",\"time_switch\":212697.46}]",
    "metadata": "{\"slice\":0,\"id\":\"acf93932-cd44-41bd-9d27-81f5a87ebc9a\",\"payload\":\"full\"}",
    "url": "https://exp02.zih.tu-dresden.de/experiments/spot_a_word_task/"
}